README.rst
setup.py
repocribro_pages/__init__.py
repocribro_pages/ext_pages.py
repocribro_pages/models.py
repocribro_pages.egg-info/PKG-INFO
repocribro_pages.egg-info/SOURCES.txt
repocribro_pages.egg-info/dependency_links.txt
repocribro_pages.egg-info/entry_points.txt
repocribro_pages.egg-info/not-zip-safe
repocribro_pages.egg-info/requires.txt
repocribro_pages.egg-info/top_level.txt
repocribro_pages/controllers/__init__.py
repocribro_pages/controllers/admin.py
repocribro_pages/controllers/pages.py