Metadata-Version: 1.1
Name: repocribro-pages
Version: 0.1
Summary: Extension of repocribro for custom static pages
Home-page: https://github.com/MarekSuchanek/repocribro-pages
Author: Marek Suchánek
Author-email: suchama4@fit.cvut.cz
License: MIT
Keywords: repocribro custom pages information cms
Platform: UNKNOWN
Classifier: Development Status :: 4 - Beta
Classifier: Environment :: Web Environment
Classifier: Environment :: Plugins
Classifier: Framework :: Flask
Classifier: Intended Audience :: Developers
Classifier: Intended Audience :: Education
Classifier: Intended Audience :: Information Technology
Classifier: Intended Audience :: Science/Research
Classifier: License :: OSI Approved :: MIT License
Classifier: Natural Language :: English
Classifier: Programming Language :: Python
Classifier: Programming Language :: Python :: 3
Classifier: Programming Language :: Python :: 3.5
Classifier: Topic :: Communications
Classifier: Topic :: Internet
Classifier: Topic :: Software Development
Classifier: Topic :: Software Development :: Version Control
